swh/datasets/__init__.py
swh/datasets/cli.py
swh/datasets/download.py
swh/datasets/shell.py
swh/datasets/luigi/__init__.py
swh/datasets/luigi/aggregate_datasets.py
swh/datasets/luigi/blobs_datasets.py
swh/datasets/luigi/file_names.py
swh/datasets/luigi/impact.py
swh/datasets/luigi/origin_contributors.py
swh/datasets/tests/conftest.py
swh/datasets/tests/test_cli.py
swh/datasets/tests/luigi/__init__.py
swh/datasets/tests/luigi/test_aggregate.py
swh/datasets/tests/luigi/test_blobs_datasets.py
swh/datasets/tests/luigi/test_file_names.py
swh/datasets/tests/luigi/test_origin_contributors.py
swh_datasets-2.1.0.dist-info/licenses/AUTHORS
swh_datasets-2.1.0.dist-info/licenses/LICENSE
swh_datasets-2.1.0.dist-info/METADATA
swh_datasets-2.1.0.dist-info/WHEEL
swh_datasets-2.1.0.dist-info/entry_points.txt
swh_datasets-2.1.0.dist-info/top_level.txt
swh_datasets-2.1.0.dist-info/RECORD
